my_pdf_package/__init__.py
my_pdf_package/pdf_processor.py
tests/__init__.py
tests/test_pdf_processor.py
pdf_processor_xyz-0.1.dist-info/LICENSE
pdf_processor_xyz-0.1.dist-info/METADATA
pdf_processor_xyz-0.1.dist-info/WHEEL
pdf_processor_xyz-0.1.dist-info/entry_points.txt
pdf_processor_xyz-0.1.dist-info/top_level.txt
pdf_processor_xyz-0.1.dist-info/RECORD
