Metadata-Version: 2.1
Name: pdf-processor-xyz
Version: 0.1
Summary: A package to process PDF files
Author: Baha Arfaoui
Author-email: baha.arfaoui01@gmail.com
Classifier: Programming Language :: Python :: 3
Classifier: License :: OSI Approved :: MIT License
Classifier: Operating System :: OS Independent
Requires-Python: >=3.6
License-File: LICENSE
Requires-Dist: marker-pdf
